proxy_information/__init__.py
proxy_information/proxy_information.py
proxy_information-0.2.dist-info/METADATA
proxy_information-0.2.dist-info/WHEEL
proxy_information-0.2.dist-info/top_level.txt
proxy_information-0.2.dist-info/RECORD
