Metadata-Version: 2.1
Name: proxy-information
Version: 0.2
Summary: A tool to verify proxy information.
Home-page: https://github.com/BlackCage/Proxy-Information-Checker
Author: BlackCage
Author-email: blackcage_faq@proton.me
Classifier: Topic :: Internet :: Proxy Servers
Classifier: Intended Audience :: Developers
Classifier: Programming Language :: Python :: 3
Classifier: Programming Language :: Python :: 3.7
Classifier: Programming Language :: Python :: 3.8
Classifier: Programming Language :: Python :: 3.9
Classifier: Programming Language :: Python :: 3.10
Requires-Dist: requests
Requires-Dist: fake-useragent
